jsearch/__init__.py
jsearch/version.py
jsearch-1.1.0.dist-info/LICENSE
jsearch-1.1.0.dist-info/METADATA
jsearch-1.1.0.dist-info/WHEEL
jsearch-1.1.0.dist-info/entry_points.txt
jsearch-1.1.0.dist-info/top_level.txt
jsearch-1.1.0.dist-info/RECORD
