Metadata-Version: 2.1
Name: jsearch
Version: 1.1.0
Summary: It implements all search algorithms
Home-page: https://github.com/sjlouji/jsearch.git
Author: Joan Louji
Author-email: sjlouji10@gmail.com
License: MIT
Platform: UNKNOWN
Classifier: License :: OSI Approved :: MIT License
Classifier: Programming Language :: Python :: 3.6
Classifier: Programming Language :: Python :: 3.7
Classifier: Programming Language :: Python :: 3.8
